.DS_Store
whacc/.DS_Store
whacc/__init__.py
whacc/analysis.py
whacc/feature_maker.py
whacc/feature_maker_temp.py
whacc/image_tools.py
whacc/model_maker.py
whacc/pole_tracker.py
whacc/retrain_LGBM.py
whacc/run_in_terminal_template.py
whacc/subset_h5_generator.py
whacc/touch_curation_GUI.py
whacc/transfer_learning.py
whacc/utils.py
whacc/__pycache__/__init__.cpython-311.pyc
whacc/__pycache__/__init__.cpython-37.pyc
whacc/__pycache__/__init__.cpython-38.pyc
whacc/__pycache__/analysis.cpython-37.pyc
whacc/__pycache__/analysis.cpython-38.pyc
whacc/__pycache__/feature_maker.cpython-37.pyc
whacc/__pycache__/feature_maker.cpython-38.pyc
whacc/__pycache__/image_tools.cpython-37.pyc
whacc/__pycache__/image_tools.cpython-38.pyc
whacc/__pycache__/model_maker.cpython-37.pyc
whacc/__pycache__/model_maker.cpython-38.pyc
whacc/__pycache__/pole_tracker.cpython-37.pyc
whacc/__pycache__/pole_tracker.cpython-38.pyc
whacc/__pycache__/retrain_LGBM.cpython-38.pyc
whacc/__pycache__/subset_h5_generator.cpython-311.pyc
whacc/__pycache__/subset_h5_generator.cpython-37.pyc
whacc/__pycache__/subset_h5_generator.cpython-38.pyc
whacc/__pycache__/touch_curation_GUI.cpython-37.pyc
whacc/__pycache__/touch_curation_GUI.cpython-38.pyc
whacc/__pycache__/transfer_learning.cpython-37.pyc
whacc/__pycache__/transfer_learning.cpython-38.pyc
whacc/__pycache__/utils.cpython-37.pyc
whacc/__pycache__/utils.cpython-38.pyc
whacc/examples/0.5 before batch processing.py
whacc/examples/1_make_h5_example.py
whacc/examples/2_predict_touches_example.py
whacc/examples/3_make_subset_H5_example.py
whacc/examples/4_augment_H5_example.py
whacc/examples/5_split_data_for_retrain_example.py
whacc/examples/6_retrain_example.py
whacc/examples/7.5_convert_h5_to_features.py
whacc/examples/7_select_TL_trials.py
whacc/examples/8_make_feature_data.py
whacc/examples/9_re_train_GBM_EXAMPLE.py
whacc/examples/CNN_+lightGBM_V5_Testing_GPU_RAM_limits_V2.py
whacc/examples/SCRATCH5.py
whacc/examples/TL_10_20_30.py
whacc/examples/__init__.py
whacc-1.4.3.dist-info/LICENSE
whacc-1.4.3.dist-info/METADATA
whacc-1.4.3.dist-info/WHEEL
whacc-1.4.3.dist-info/top_level.txt
whacc-1.4.3.dist-info/RECORD
