Metadata-Version: 2.1
Name: whacc
Version: 1.4.3
Summary: Automatic and customizable pipeline for creating a CNN + light GBM model to predict whiskers contacting objects
Home-page: https://github.com/hireslab/whacc
Author: Phillip Maire
Author-email: phillip.maire@gmail.com
License: MIT
Platform: UNKNOWN
Classifier: Programming Language :: Python :: 3
Classifier: License :: OSI Approved :: MIT License
Classifier: Operating System :: OS Independent
Requires-Python: >=3.6
Requires-Dist: natsort (==7.1.1)
